edfi_lms_ds_loader/__init__.py
edfi_lms_ds_loader/__main__.py
edfi_lms_ds_loader/db_operations/__init__.py
edfi_lms_ds_loader/db_operations/MSSQL_sql_builder.py
edfi_lms_ds_loader/db_operations/PGSQL_sql_builder.py
edfi_lms_ds_loader/df_to_db.py
edfi_lms_ds_loader/helpers/__init__.py
edfi_lms_ds_loader/helpers/argparser.py
edfi_lms_ds_loader/helpers/assignment_splitter.py
edfi_lms_ds_loader/helpers/constants.py
edfi_lms_ds_loader/loader_facade.py
edfi_lms_ds_loader/migrator.py
edfi_lms_ds_loader/scripts/mssql/0001_initialize_lms_database.sql
edfi_lms_ds_loader/scripts/mssql/0002_create_processed_files_table.sql
edfi_lms_ds_loader/scripts/mssql/0003_create_user_tables.sql
edfi_lms_ds_loader/scripts/mssql/0004_create_section_tables.sql
edfi_lms_ds_loader/scripts/mssql/0005_create_assignment_tables.sql
edfi_lms_ds_loader/scripts/mssql/0006_create_section_association_tables.sql
edfi_lms_ds_loader/scripts/mssql/0007_create_assignment_submission_tables.sql
edfi_lms_ds_loader/scripts/mssql/0008_create_section_activity_tables.sql
edfi_lms_ds_loader/scripts/mssql/0009_create_system_activity_tables.sql
edfi_lms_ds_loader/scripts/mssql/0010_create_attendance_tables.sql
edfi_lms_ds_loader/scripts/mssql/0011_remove_startdate_enddate_from_sectionassociation.sql
edfi_lms_ds_loader/scripts/mssql/0012_add_mapping_columns_for_edfi_student_and_section.sql
edfi_lms_ds_loader/scripts/postgresql/0001_initialize_lms_database.sql
edfi_lms_ds_loader/scripts/postgresql/0002_create_user_tables.sql
edfi_lms_ds_loader/scripts/postgresql/0003_create_processed_files_table.sql
edfi_lms_ds_loader/scripts/postgresql/0004_create_section_tables.sql
edfi_lms_ds_loader/scripts/postgresql/0005_create_assignment_tables.sql
edfi_lms_ds_loader/scripts/postgresql/0006_create_section_association_tables.sql
edfi_lms_ds_loader/scripts/postgresql/0007_create_assignment_submission_tables.sql
edfi_lms_ds_loader/scripts/postgresql/0008_create_section_activity_tables.sql
edfi_lms_ds_loader-1.2.2.dist-info/METADATA
edfi_lms_ds_loader-1.2.2.dist-info/WHEEL
edfi_lms_ds_loader-1.2.2.dist-info/RECORD
