Metadata-Version: 2.1
Name: edfi-lms-ds-loader
Version: 1.2.2
Summary: Ed-Fi LMS Toolkit Data Store Loader
Home-page: https://docs.ed-fi.org/getting-started/edfi-exchange/technology/ed-fi-lms-toolkit
License: Apache-2.0
Author: Ed-Fi Alliance, LLC and contributors
Requires-Python: >3.9.1,<4.0.0
Classifier: License :: OSI Approved :: Apache Software License
Classifier: Programming Language :: Python :: 3
Classifier: Programming Language :: Python :: 3.10
Classifier: Programming Language :: Python :: 3.11
Classifier: Programming Language :: Python :: 3.12
Requires-Dist: configargparse (>=1.2.3,<2.0.0)
Requires-Dist: cryptography (>=44.0.1,<45.0.0)
Requires-Dist: edfi-lms-extractor-lib (>=1.1.6,<2.0.0)
Requires-Dist: edfi-lms-file-utils (>=1.0.6,<2.0.0)
Requires-Dist: edfi-sql-adapter (>=1.0.3,<2.0.0)
Requires-Dist: errorhandler (>=2.0.1,<3.0.0)
Requires-Dist: numpy (>=1,<2)
Requires-Dist: pandas (<2.0.0)
Requires-Dist: psycopg2 (>=2.8.6,<3.0.0)
Requires-Dist: pyodbc (>=4.0.30,<5.0.0)
Requires-Dist: python-dotenv (>=0.15.0,<0.16.0)
Requires-Dist: sqlalchemy (==1.3.23)
Requires-Dist: sqlparse (>=0.4.1,<0.6.0)
Project-URL: Repository, https://github.com/Ed-Fi-Exchange-OSS/LMS-Toolkit
